FabricSync/Meta.py
FabricSync/__init__.py
FabricSync/BQ/APIClient.py
FabricSync/BQ/Auth.py
FabricSync/BQ/BigQueryAPI.py
FabricSync/BQ/Constants.py
FabricSync/BQ/Core.py
FabricSync/BQ/Enum.py
FabricSync/BQ/Exceptions.py
FabricSync/BQ/Experimental.py
FabricSync/BQ/Expiration.py
FabricSync/BQ/FileSystem.py
FabricSync/BQ/GoogleStorageAPI.py
FabricSync/BQ/Http.py
FabricSync/BQ/Lakehouse.py
FabricSync/BQ/Loader.py
FabricSync/BQ/Logging.py
FabricSync/BQ/Maintenance.py
FabricSync/BQ/Metadata.py
FabricSync/BQ/Metastore.py
FabricSync/BQ/Mirror.py
FabricSync/BQ/ModelValidation.py
FabricSync/BQ/Schedule.py
FabricSync/BQ/SessionManager.py
FabricSync/BQ/Setup.py
FabricSync/BQ/Sync.py
FabricSync/BQ/SyncCore.py
FabricSync/BQ/SyncUtils.py
FabricSync/BQ/Threading.py
FabricSync/BQ/Utils.py
FabricSync/BQ/Validation.py
FabricSync/BQ/Warnings.py
FabricSync/BQ/__init__.py
FabricSync/BQ/Model/Config.py
FabricSync/BQ/Model/Core.py
FabricSync/BQ/Model/Maintenance.py
FabricSync/BQ/Model/Schedule.py
FabricSync/BQ/Model/__init__.py
fabricsync-2.2.11.dist-info/licenses/LICENSE
fabricsync-2.2.11.dist-info/METADATA
fabricsync-2.2.11.dist-info/WHEEL
fabricsync-2.2.11.dist-info/top_level.txt
fabricsync-2.2.11.dist-info/RECORD
