Metadata-Version: 2.4
Name: FabricSync
Version: 2.2.11
Summary: Fabric BigQuery Data Sync Utility
Author-email: "Praveen Singh (MSFT)" <Singh.Praveen@microsoft.com>, Tonio Lora <tonio.lora@microsoft.com>, Shane Ochotny <Shane.Ochotny@microsoft.com>
License-Expression: MIT
Project-URL: Homepage, https://github.com/microsoft/FabricBQSync
Project-URL: Documentation, https://github.com/microsoft/FabricBQSync/blob/main/Docs/Home.md
Project-URL: Repository, https://github.com/microsoft/FabricBQSync.git
Project-URL: Issues, https://github.com/microsoft/FabricBQSync/issues
Keywords: Fabric,BigQuery,Data Sync,Mirror,ETL
Classifier: Development Status :: 4 - Beta
Classifier: Intended Audience :: Developers
Classifier: Programming Language :: Python
Classifier: Programming Language :: Python :: 3.8
Classifier: Programming Language :: Python :: 3.9
Classifier: Programming Language :: Python :: 3.10
Classifier: Programming Language :: Python :: 3.11
Classifier: Programming Language :: Python :: 3.12
Classifier: Topic :: Software Development :: Libraries :: Python Modules
Classifier: Topic :: Utilities
Requires-Python: >=3.11.8
License-File: LICENSE
Requires-Dist: virtualenv
Requires-Dist: fsspec-wrapper
Requires-Dist: nni
Requires-Dist: datasets
Requires-Dist: mlflow-skinny
Requires-Dist: db-dtypes
Requires-Dist: google-cloud-bigquery
Requires-Dist: google-cloud-storage
Requires-Dist: pydantic
Requires-Dist: pygithub
Requires-Dist: pyspark
Requires-Dist: delta-spark
Dynamic: license-file
